<TextureAtlas imagePath="sprites.png">
	<SubTexture name="bg1.png" x="374" y="946" width="32" height="32"/>
	<SubTexture name="bg2.png" x="635" y="68" width="32" height="32"/>
	<SubTexture name="bg3.png" x="635" y="34" width="32" height="32"/>
	<SubTexture name="bg4.png" x="635" y="0" width="32" height="32"/>
	<SubTexture name="completeoff.png" x="0" y="428" width="400" height="223"/>
	<SubTexture name="completeon.png" x="0" y="203" width="400" height="223"/>
	<SubTexture name="finishoff.png" x="0" y="653" width="400" height="223"/>
	<SubTexture name="finishon.png" x="402" y="428" width="400" height="223"/>
	<SubTexture name="handclose.png" x="601" y="136" width="32" height="32"/>
	<SubTexture name="handopen.png" x="601" y="102" width="32" height="32"/>
	<SubTexture name="help1.png" x="0" y="0" width="497" height="201"/>
	<SubTexture name="helpoff.png" x="402" y="203" width="400" height="223"/>
	<SubTexture name="helpon.png" x="402" y="653" width="400" height="223"/>
	<SubTexture name="ice.png" x="578" y="980" width="32" height="32"/>
	<SubTexture name="icegod1.png" x="578" y="946" width="32" height="32"/>
	<SubTexture name="icegod10.png" x="544" y="946" width="32" height="32"/>
	<SubTexture name="icegod11.png" x="544" y="912" width="32" height="32"/>
	<SubTexture name="icegod12.png" x="544" y="878" width="32" height="32"/>
	<SubTexture name="icegod2.png" x="578" y="912" width="32" height="32"/>
	<SubTexture name="icegod3.png" x="578" y="878" width="32" height="32"/>
	<SubTexture name="icegod4.png" x="567" y="136" width="32" height="32"/>
	<SubTexture name="icegod5.png" x="567" y="102" width="32" height="32"/>
	<SubTexture name="icegod6.png" x="567" y="68" width="32" height="32"/>
	<SubTexture name="icegod7.png" x="567" y="34" width="32" height="32"/>
	<SubTexture name="icegod8.png" x="567" y="0" width="32" height="32"/>
	<SubTexture name="icegod9.png" x="544" y="980" width="32" height="32"/>
	<SubTexture name="invisible1.png" x="533" y="136" width="32" height="32"/>
	<SubTexture name="invisible10.png" x="533" y="34" width="32" height="32"/>
	<SubTexture name="invisible11.png" x="533" y="68" width="32" height="32"/>
	<SubTexture name="invisible12.png" x="533" y="102" width="32" height="32"/>
	<SubTexture name="invisible13.png" x="533" y="136" width="32" height="32"/>
	<SubTexture name="invisible2.png" x="533" y="102" width="32" height="32"/>
	<SubTexture name="invisible3.png" x="533" y="68" width="32" height="32"/>
	<SubTexture name="invisible4.png" x="533" y="34" width="32" height="32"/>
	<SubTexture name="invisible5.png" x="533" y="0" width="32" height="32"/>
	<SubTexture name="invisible6.png" x="510" y="980" width="32" height="32"/>
	<SubTexture name="invisible7.png" x="510" y="946" width="32" height="32"/>
	<SubTexture name="invisible8.png" x="510" y="980" width="32" height="32"/>
	<SubTexture name="invisible9.png" x="533" y="0" width="32" height="32"/>
	<SubTexture name="item1.png" x="510" y="912" width="32" height="32"/>
	<SubTexture name="item2.png" x="510" y="878" width="32" height="32"/>
	<SubTexture name="item3.png" x="499" y="136" width="32" height="32"/>
	<SubTexture name="item4.png" x="499" y="102" width="32" height="32"/>
	<SubTexture name="item5.png" x="499" y="68" width="32" height="32"/>
	<SubTexture name="item6.png" x="499" y="34" width="32" height="32"/>
	<SubTexture name="item7.png" x="499" y="0" width="32" height="32"/>
	<SubTexture name="item8.png" x="476" y="980" width="32" height="32"/>
	<SubTexture name="main1.png" x="476" y="946" width="32" height="32"/>
	<SubTexture name="main2.png" x="476" y="912" width="32" height="32"/>
	<SubTexture name="saw1.png" x="476" y="878" width="32" height="32"/>
	<SubTexture name="saw10.png" x="442" y="912" width="32" height="32"/>
	<SubTexture name="saw11.png" x="442" y="946" width="32" height="32"/>
	<SubTexture name="saw12.png" x="442" y="980" width="32" height="32"/>
	<SubTexture name="saw13.png" x="476" y="878" width="32" height="32"/>
	<SubTexture name="saw2.png" x="442" y="980" width="32" height="32"/>
	<SubTexture name="saw3.png" x="442" y="946" width="32" height="32"/>
	<SubTexture name="saw4.png" x="442" y="912" width="32" height="32"/>
	<SubTexture name="saw5.png" x="442" y="878" width="32" height="32"/>
	<SubTexture name="saw6.png" x="408" y="980" width="32" height="32"/>
	<SubTexture name="saw7.png" x="408" y="946" width="32" height="32"/>
	<SubTexture name="saw8.png" x="408" y="980" width="32" height="32"/>
	<SubTexture name="saw9.png" x="442" y="878" width="32" height="32"/>
	<SubTexture name="sleep1.png" x="408" y="912" width="32" height="32"/>
	<SubTexture name="sleep2.png" x="408" y="878" width="32" height="32"/>
	<SubTexture name="sleep3.png" x="374" y="980" width="32" height="32"/>
	<SubTexture name="sleep4.png" x="635" y="102" width="32" height="32"/>
	<SubTexture name="sleep5.png" x="374" y="912" width="32" height="32"/>
	<SubTexture name="sleep6.png" x="612" y="980" width="32" height="32"/>
	<SubTexture name="sleep7.png" x="612" y="946" width="32" height="32"/>
	<SubTexture name="soundoff.png" x="601" y="34" width="32" height="32"/>
	<SubTexture name="soundon.png" x="601" y="0" width="32" height="32"/>
	<SubTexture name="tiles10.png" x="306" y="878" width="32" height="32"/>
	<SubTexture name="tiles11.png" x="272" y="980" width="32" height="32"/>
	<SubTexture name="tiles12.png" x="272" y="946" width="32" height="32"/>
	<SubTexture name="tiles13.png" x="272" y="912" width="32" height="32"/>
	<SubTexture name="tiles14.png" x="272" y="878" width="32" height="32"/>
	<SubTexture name="tiles15.png" x="238" y="980" width="32" height="32"/>
	<SubTexture name="tiles16.png" x="238" y="946" width="32" height="32"/>
	<SubTexture name="tiles17.png" x="238" y="912" width="32" height="32"/>
	<SubTexture name="tiles18.png" x="238" y="878" width="32" height="32"/>
	<SubTexture name="tiles19.png" x="204" y="980" width="32" height="32"/>
	<SubTexture name="tiles20.png" x="204" y="946" width="32" height="32"/>
	<SubTexture name="tiles21.png" x="204" y="912" width="32" height="32"/>
	<SubTexture name="tiles22.png" x="204" y="878" width="32" height="32"/>
	<SubTexture name="tiles23.png" x="170" y="980" width="32" height="32"/>
	<SubTexture name="tiles24.png" x="170" y="946" width="32" height="32"/>
	<SubTexture name="tiles25.png" x="170" y="912" width="32" height="32"/>
	<SubTexture name="tiles26.png" x="374" y="878" width="32" height="32"/>
	<SubTexture name="tiles27.png" x="340" y="980" width="32" height="32"/>
	<SubTexture name="tiles28.png" x="136" y="946" width="32" height="32"/>
	<SubTexture name="tiles29.png" x="136" y="912" width="32" height="32"/>
	<SubTexture name="tiles30.png" x="136" y="878" width="32" height="32"/>
	<SubTexture name="tiles31.png" x="102" y="980" width="32" height="32"/>
	<SubTexture name="tiles32.png" x="102" y="946" width="32" height="32"/>
	<SubTexture name="tiles33.png" x="102" y="912" width="32" height="32"/>
	<SubTexture name="tiles34.png" x="102" y="878" width="32" height="32"/>
	<SubTexture name="tiles35.png" x="68" y="980" width="32" height="32"/>
	<SubTexture name="tiles36.png" x="68" y="946" width="32" height="32"/>
	<SubTexture name="tiles37.png" x="170" y="878" width="32" height="32"/>
	<SubTexture name="tiles38.png" x="68" y="878" width="32" height="32"/>
	<SubTexture name="tiles39.png" x="34" y="980" width="32" height="32"/>
	<SubTexture name="tiles40.png" x="34" y="946" width="32" height="32"/>
	<SubTexture name="tiles41.png" x="34" y="912" width="32" height="32"/>
	<SubTexture name="tiles42.png" x="68" y="912" width="32" height="32"/>
	<SubTexture name="tiles43.png" x="0" y="980" width="32" height="32"/>
	<SubTexture name="tiles44.png" x="0" y="946" width="32" height="32"/>
	<SubTexture name="tiles45.png" x="34" y="878" width="32" height="32"/>
	<SubTexture name="tiles6.png" x="340" y="878" width="32" height="32"/>
	<SubTexture name="tiles7.png" x="306" y="980" width="32" height="32"/>
	<SubTexture name="tiles8.png" x="306" y="946" width="32" height="32"/>
	<SubTexture name="tiles9.png" x="306" y="912" width="32" height="32"/>
	<SubTexture name="torch1.png" x="0" y="912" width="32" height="32"/>
	<SubTexture name="torch2.png" x="0" y="878" width="32" height="32"/>
	<SubTexture name="torch3.png" x="340" y="912" width="32" height="32"/>
	<SubTexture name="torch4.png" x="340" y="946" width="32" height="32"/>
	<SubTexture name="torchoff1.png" x="136" y="980" width="32" height="32"/>
	<SubTexture name="torchoff2.png" x="612" y="878" width="32" height="32"/>
	<SubTexture name="torchoff3.png" x="612" y="912" width="32" height="32"/>
	<SubTexture name="torchoff4.png" x="601" y="68" width="32" height="32"/>
	<SubTexture name="wakeup1.png" x="612" y="946" width="32" height="32"/>
	<SubTexture name="wakeup2.png" x="612" y="980" width="32" height="32"/>
	<SubTexture name="wakeup3.png" x="374" y="912" width="32" height="32"/>
	<SubTexture name="wakeup4.png" x="635" y="102" width="32" height="32"/>
	<SubTexture name="wakeup5.png" x="374" y="980" width="32" height="32"/>
	<SubTexture name="wakeup6.png" x="408" y="878" width="32" height="32"/>
	<SubTexture name="wakeup7.png" x="408" y="912" width="32" height="32"/>
</TextureAtlas>